{"FORM": {"avg_volume": 1966092, "market_cap": 8654733603}, "APGE": {"avg_volume": 2496517, "market_cap": 10146095118}, "FTI": {"avg_volume": 4821731, "market_cap": 28630782250}, "CENX": {"avg_volume": 1926677, "market_cap": 4262317198}, "MLTX": {"avg_volume": 1071718, "market_cap": 1646415805}, "TECK": {"avg_volume": 3149797, "market_cap": 27625138939}, "LGN": {"avg_volume": 1560710, "market_cap": 11247662092}, "DINO": {"avg_volume": 2360184, "market_cap": 15323412145}, "PAAS": {"avg_volume": 4859559, "market_cap": 17882093421}, "SPHR": {"avg_volume": 698133, "market_cap": 5088577434}, "POWL": {"avg_volume": 721215, "market_cap": 8786220722}, "TTC": {"avg_volume": 834273, "market_cap": 9022998346}, "AMD": {"avg_volume": 35869193, "market_cap": 839938671269}, "SCCO": {"avg_volume": 1331578, "market_cap": 148410358721}, "EQNR": {"avg_volume": 4031693, "market_cap": 84870123061}, "SMTC": {"avg_volume": 3602425, "market_cap": 12194884533}, "LYB": {"avg_volume": 5606259, "market_cap": 18863541690}, "NE": {"avg_volume": 1554268, "market_cap": 6475969891}, "PR": {"avg_volume": 11384898, "market_cap": 16502948157}, "AIR": {"avg_volume": 413687, "market_cap": 5235363670}, "VAL": {"avg_volume": 945195, "market_cap": 5332387060}, "AMKR": {"avg_volume": 5491581, "market_cap": 16280267057}, "USO": {"avg_volume": 8837953}, "MU": {"avg_volume": 50325458, "market_cap": 988410984659}, "ACMR": {"avg_volume": 1668243, "market_cap": 6187372286}, "DVN": {"avg_volume": 14326270, "market_cap": 49925053310}, "ONTO": {"avg_volume": 1264266, "market_cap": 14710665615}, "CGON": {"avg_volume": 1040084, "market_cap": 6264360057}, "SLVP": {"avg_volume": 359771}, "APA": {"avg_volume": 5982275, "market_cap": 12194722831}, "JBHT": {"avg_volume": 981609, "market_cap": 27880304137}, "CHYM": {"avg_volume": 5141862, "market_cap": 8496726509}, "AG": {"avg_volume": 12136766, "market_cap": 7986722385}, "STM": {"avg_volume": 12549683, "market_cap": 57339432655}, "WDC": {"avg_volume": 8196701, "market_cap": 168035989049}, "MRNA": {"avg_volume": 7774527, "market_cap": 26668004104}, "ESLT": {"avg_volume": 106574, "market_cap": 35005927351}, "KEYS": {"avg_volume": 1544506, "market_cap": 53611584434}, "CAT": {"avg_volume": 2979661, "market_cap": 412697332394}, "LFUS": {"avg_volume": 340288, "market_cap": 10224683282}, "SQM": {"avg_volume": 1153839, "market_cap": 20133181071}, "AXSM": {"avg_volume": 912919, "market_cap": 12094588740}, "BMRN": {"avg_volume": 2019673, "market_cap": 11326467771}, "VSAT": {"avg_volume": 2508713, "market_cap": 9278495000}, "RIO": {"avg_volume": 2603781, "market_cap": 147728749797}, "MPC": {"avg_volume": 2319966, "market_cap": 88364839652}, "CHRD": {"avg_volume": 793575, "market_cap": 6999114413}, "LNTH": {"avg_volume": 960956, "market_cap": 6808142974}, "DVA": {"avg_volume": 857690, "market_cap": 14924616733}, "PBF": {"avg_volume": 2910230, "market_cap": 6993213083}, "MUR": {"avg_volume": 1795671, "market_cap": 5030136643}, "BLSH": {"avg_volume": 1501347, "market_cap": 3692637282}, "SOLS": {"avg_volume": 2645788, "market_cap": 9524656476}, "DOCN": {"avg_volume": 3643933, "market_cap": 12137032238}, "NVST": {"avg_volume": 3094982, "market_cap": 4397722056}, "ON": {"avg_volume": 13150488, "market_cap": 34516871991}, "FRO": {"avg_volume": 3023500, "market_cap": 8368394469}, "LITE": {"avg_volume": 5533011, "market_cap": 56489025329}, "SGML": {"avg_volume": 2962753, "market_cap": 1214780779}, "CEG": {"avg_volume": 3616785, "market_cap": 91139577214}, "LRCX": {"avg_volume": 11001048, "market_cap": 405799905500}, "OXY": {"avg_volume": 11056333, "market_cap": 53461615178}, "SU": {"avg_volume": 4129445, "market_cap": 71718464761}, "COHR": {"avg_volume": 5856788, "market_cap": 54982476445}, "ATI": {"avg_volume": 1769222, "market_cap": 25876840765}, "HOG": {"avg_volume": 2797086, "market_cap": 2766977302}, "SYNA": {"avg_volume": 1099243, "market_cap": 4550801754}, "OGN": {"avg_volume": 7166748, "market_cap": 3545227345}, "NTLA": {"avg_volume": 6788779, "market_cap": 1693014778}, "MKSI": {"avg_volume": 1303719, "market_cap": 23154802697}, "LSCC": {"avg_volume": 2191656, "market_cap": 17667162742}, "VRT": {"avg_volume": 6068560, "market_cap": 114664159532}, "ZIM": {"avg_volume": 1265681, "market_cap": 3000337140}, "GLW": {"avg_volume": 14341960, "market_cap": 140619613701}, "ENTG": {"avg_volume": 3277751, "market_cap": 20358702964}, "RMBS": {"avg_volume": 2979632, "market_cap": 10813696700}, "KNX": {"avg_volume": 4182820, "market_cap": 12320295030}, "FCX": {"avg_volume": 14635782, "market_cap": 85534811967}, "VICR": {"avg_volume": 895423, "market_cap": 11386691171}, "VKTX": {"avg_volume": 2378961, "market_cap": 4340029059}, "VG": {"avg_volume": 16638778, "market_cap": 32545337544}, "XOP": {"avg_volume": 3703366}, "TPL": {"avg_volume": 403510, "market_cap": 28122254276}, "COGT": {"avg_volume": 2378872, "market_cap": 6662143762}, "WFRD": {"avg_volume": 1288107, "market_cap": 5862101668}, "ENPH": {"avg_volume": 7762542, "market_cap": 5573087712}, "INTC": {"avg_volume": 132141028, "market_cap": 500740366195}, "AGI": {"avg_volume": 4017282, "market_cap": 11878721586}, "PTEN": {"avg_volume": 9042536, "market_cap": 3743029928}, "AMAT": {"avg_volume": 9181288, "market_cap": 453731919549}, "CGNX": {"avg_volume": 2356016, "market_cap": 10226475390}, "OSK": {"avg_volume": 714929, "market_cap": 9007270516}, "JAZZ": {"avg_volume": 913137, "market_cap": 15090365069}, "CNC": {"avg_volume": 5690389, "market_cap": 33084399000}, "TTMI": {"avg_volume": 2654990, "market_cap": 14227458083}, "HWM": {"avg_volume": 2772892, "market_cap": 110513684460}, "OIH": {"avg_volume": 387005}, "BG": {"avg_volume": 1681436, "market_cap": 22579827690}, "AA": {"avg_volume": 5216758, "market_cap": 12422715677}, "ENS": {"avg_volume": 486123, "market_cap": 7167638955}, "EOG": {"avg_volume": 3759514, "market_cap": 73976776206}, "CNQ": {"avg_volume": 9447732, "market_cap": 89403962650}, "LBRT": {"avg_volume": 3608286, "market_cap": 4048778943}, "AKAM": {"avg_volume": 4990119, "market_cap": 17540754884}, "SW": {"avg_volume": 5504429, "market_cap": 23081663192}, "STNG": {"avg_volume": 956667, "market_cap": 3944406610}, "TEX": {"avg_volume": 1288509, "market_cap": 7384101812}, "AEM": {"avg_volume": 2533712, "market_cap": 69732554346}, "LEA": {"avg_volume": 610607, "market_cap": 7031097406}, "VLO": {"avg_volume": 3055299, "market_cap": 88082144802}, "ATRO": {"avg_volume": 739732, "market_cap": 3444519028}, "SKYT": {"avg_volume": 977762, "market_cap": 1534445487}, "SM": {"avg_volume": 4074686, "market_cap": 7275174167}, "MTSI": {"avg_volume": 1599374, "market_cap": 21374260620}, "DOW": {"avg_volume": 12191205, "market_cap": 21416831940}, "EWY": {"avg_volume": 19747125}, "NOV": {"avg_volume": 4271173, "market_cap": 6983969492}, "WLK": {"avg_volume": 1111338, "market_cap": 9851078858}, "COPX": {"avg_volume": 3709095}, "GFS": {"avg_volume": 4707694, "market_cap": 32164842244}, "PBR": {"avg_volume": 16538607, "market_cap": 115096387497}, "VIAV": {"avg_volume": 7269155, "market_cap": 9559068821}, "CE": {"avg_volume": 1862204, "market_cap": 5140979945}, "KRMN": {"avg_volume": 2900439, "market_cap": 6419573741}, "MSGS": {"avg_volume": 254332, "market_cap": 9406775560}, "MGA": {"avg_volume": 1380387, "market_cap": 18141043845}, "REMX": {"avg_volume": 1002262}, "TAN": {"avg_volume": 1462035}, "SLB": {"avg_volume": 14185153, "market_cap": 71075042572}, "ROIV": {"avg_volume": 5925995, "market_cap": 24818425402}, "STX": {"avg_volume": 4320277, "market_cap": 177368084369}, "MTDR": {"avg_volume": 1726100, "market_cap": 6580204457}, "ALB": {"avg_volume": 2273061, "market_cap": 14364440851}, "FIVE": {"avg_volume": 1247534, "market_cap": 10940738182}, "TSEM": {"avg_volume": 2184946, "market_cap": 26997512363}, "CVE": {"avg_volume": 8164846, "market_cap": 51273199970}, "TER": {"avg_volume": 4284106, "market_cap": 51401403323}, "OVV": {"avg_volume": 3387655, "market_cap": 15869120741}, "TPR": {"avg_volume": 2552479, "market_cap": 28796421629}, "GE": {"avg_volume": 5543330, "market_cap": 365596330212}, "TM": {"avg_volume": 513863, "market_cap": 212298120167}, "HAL": {"avg_volume": 11749105, "market_cap": 29552194875}, "RVMD": {"avg_volume": 3042193, "market_cap": 38668106323}, "CIEN": {"avg_volume": 2661766, "market_cap": 56949572615}, "ODFL": {"avg_volume": 1924856, "market_cap": 48775842015}, "CAVA": {"avg_volume": 3098311, "market_cap": 8007577600}, "COP": {"avg_volume": 7634285, "market_cap": 136815638328}, "B": {"avg_volume": 11725721, "market_cap": 58683069738}, "AEIS": {"avg_volume": 926654, "market_cap": 11772135800}, "CAR": {"avg_volume": 2032652, "market_cap": 5687499543}, "DAR": {"avg_volume": 2419348, "market_cap": 9600801974}, "SITM": {"avg_volume": 562859, "market_cap": 17655034010}}