{"LTH": {"avg_volume": 2938862, "market_cap": 9324828558}, "APA": {"avg_volume": 6113278, "market_cap": 11820043905}, "WPM": {"avg_volume": 2128371, "market_cap": 49976467430}, "SGML": {"avg_volume": 3132752, "market_cap": 1334689916}, "AGI": {"avg_volume": 3961966, "market_cap": 12372180623}, "FDX": {"avg_volume": 2111913, "market_cap": 75087160628}, "GTLS": {"avg_volume": 1211696, "market_cap": 10046282746}, "CHKP": {"avg_volume": 1584878, "market_cap": 13700461864}, "CSGP": {"avg_volume": 7446797, "market_cap": 11593218499}, "GOOGL": {"avg_volume": 31284280, "market_cap": 4358514980841}, "FNV": {"avg_volume": 815183, "market_cap": 39635669349}, "SRAD": {"avg_volume": 3614224, "market_cap": 4572453121}, "BBWI": {"avg_volume": 5975169, "market_cap": 4097751622}, "FSLR": {"avg_volume": 2502213, "market_cap": 24481099889}, "AA": {"avg_volume": 5233029, "market_cap": 12846262202}, "PSLV": {"avg_volume": 8854513, "market_cap": 12168874039}, "UI": {"avg_volume": 126991, "market_cap": 33347063023}, "PINS": {"avg_volume": 18334700, "market_cap": 12614743260}, "TKO": {"avg_volume": 1460698, "market_cap": 13824038443}, "GH": {"avg_volume": 2747927, "market_cap": 21222619041}, "WT": {"avg_volume": 3225472, "market_cap": 2939531046}, "TMDX": {"avg_volume": 1328856, "market_cap": 2461773806}, "COIN": {"avg_volume": 9174574, "market_cap": 41908705977}, "SQM": {"avg_volume": 1204624, "market_cap": 20905831864}, "PSKY": {"avg_volume": 9067644, "market_cap": 10531418305}, "CHTR": {"avg_volume": 3553314, "market_cap": 18456247706}, "LBRDK": {"avg_volume": 2108927, "market_cap": 4406815156}, "EGO": {"avg_volume": 3275141, "market_cap": 7878606463}, "RIVN": {"avg_volume": 34261314, "market_cap": 25300001993}, "SYM": {"avg_volume": 2144244, "market_cap": 5551680458}, "CNM": {"avg_volume": 2638621, "market_cap": 8584663343}, "TEX": {"avg_volume": 1310589, "market_cap": 7706192522}, "DB": {"avg_volume": 2900361, "market_cap": 68433864314}, "GDX": {"avg_volume": 21983935}, "COP": {"avg_volume": 7849553, "market_cap": 132842779638}, "MIR": {"avg_volume": 4006226, "market_cap": 4159147206}, "PRMB": {"avg_volume": 3762065, "market_cap": 8705216719}, "CVE": {"avg_volume": 8292209, "market_cap": 49231220888}, "AAPL": {"avg_volume": 53960956, "market_cap": 4631217201493}, "WRBY": {"avg_volume": 3155056, "market_cap": 3564877512}, "PRIM": {"avg_volume": 2182530, "market_cap": 4698477288}, "RKT": {"avg_volume": 27739944, "market_cap": 40715494670}, "SN": {"avg_volume": 1941762, "market_cap": 21603084990}, "APD": {"avg_volume": 1263893, "market_cap": 66699545605}, "ZIM": {"avg_volume": 1279267, "market_cap": 2888856311}, "DKS": {"avg_volume": 1162208, "market_cap": 19509762632}, "OSCR": {"avg_volume": 7292266, "market_cap": 9207596496}, "DVN": {"avg_volume": 14519045, "market_cap": 48708212680}, "TER": {"avg_volume": 4315465, "market_cap": 56292562410}, "CHWY": {"avg_volume": 9274344, "market_cap": 8548777098}, "REGN": {"avg_volume": 998240, "market_cap": 69667635592}, "SEI": {"avg_volume": 2362213, "market_cap": 4386025722}, "GOOG": {"avg_volume": 21406924, "market_cap": 4332279523093}, "COLB": {"avg_volume": 2777732, "market_cap": 9278166009}, "LEU": {"avg_volume": 882804, "market_cap": 3365031473}, "CENX": {"avg_volume": 1940453, "market_cap": 4421170498}, "AES": {"avg_volume": 9952102, "market_cap": 10540470807}, "HPQ": {"avg_volume": 18875615, "market_cap": 22149738923}, "NE": {"avg_volume": 1550203, "market_cap": 6377051576}, "GAP": {"avg_volume": 7930614, "market_cap": 7005189706}, "PR": {"avg_volume": 11510789, "market_cap": 16034067255}, "HIMS": {"avg_volume": 24393599, "market_cap": 7957515801}, "B": {"avg_volume": 11905937, "market_cap": 61605469391}, "FXI": {"avg_volume": 27853368}, "CAR": {"avg_volume": 2370702, "market_cap": 5517409649}, "FOX": {"avg_volume": 1641699, "market_cap": 20470156785}, "RDDT": {"avg_volume": 4887093, "market_cap": 37604715168}, "OSK": {"avg_volume": 720069, "market_cap": 9124490330}, "AU": {"avg_volume": 2913577, "market_cap": 41511738987}, "TPL": {"avg_volume": 433666, "market_cap": 27439407849}, "ATEC": {"avg_volume": 3543237, "market_cap": 1473301530}, "RVTY": {"avg_volume": 1437625, "market_cap": 12527047012}, "VTR": {"avg_volume": 4411403, "market_cap": 44076148867}, "ALHC": {"avg_volume": 5836783, "market_cap": 4099531694}, "TTAN": {"avg_volume": 1541067, "market_cap": 7411438145}, "CHRW": {"avg_volume": 1773236, "market_cap": 22808433627}, "HALO": {"avg_volume": 1770797, "market_cap": 9038310238}, "UPST": {"avg_volume": 4717367, "market_cap": 3133596929}, "CHDN": {"avg_volume": 1021217, "market_cap": 5960479338}, "OHI": {"avg_volume": 2329738, "market_cap": 14383836372}, "DHI": {"avg_volume": 2362998, "market_cap": 42984998257}, "CCJ": {"avg_volume": 3185059, "market_cap": 41806809627}, "MP": {"avg_volume": 5983306, "market_cap": 9294538794}, "DOCU": {"avg_volume": 3836822, "market_cap": 9390655879}, "MUR": {"avg_volume": 1826463, "market_cap": 4838048190}, "VFC": {"avg_volume": 7558392, "market_cap": 6579660258}, "LCID": {"avg_volume": 17800755, "market_cap": 2165925358}, "UHS": {"avg_volume": 1002271, "market_cap": 9417640568}, "FLR": {"avg_volume": 2712144, "market_cap": 7086850757}, "KWEB": {"avg_volume": 26233241}, "CE": {"avg_volume": 1950207, "market_cap": 5145366129}, "AMT": {"avg_volume": 3224197, "market_cap": 78544910796}, "CACI": {"avg_volume": 309371, "market_cap": 10746315586}, "SIL": {"avg_volume": 1600378}, "NFG": {"avg_volume": 796423, "market_cap": 7517296989}, "RCL": {"avg_volume": 2758562, "market_cap": 76534799562}, "TIGO": {"avg_volume": 1738675, "market_cap": 16244818256}, "BZ": {"avg_volume": 3852717, "market_cap": 6151966166}, "ADM": {"avg_volume": 3696208, "market_cap": 38754126101}, "G": {"avg_volume": 2965937, "market_cap": 4978406340}, "CROX": {"avg_volume": 1223009, "market_cap": 6597791400}, "CQQQ": {"avg_volume": 1323784}, "TLN": {"avg_volume": 807934, "market_cap": 18439312345}, "NEM": {"avg_volume": 7994394, "market_cap": 101727103858}, "SM": {"avg_volume": 4187407, "market_cap": 6667411246}, "HUM": {"avg_volume": 1605900, "market_cap": 47090521676}, "LLY": {"avg_volume": 3252159, "market_cap": 1059905961155}, "TSCO": {"avg_volume": 12687588, "market_cap": 15959001974}, "COPX": {"avg_volume": 3750980}, "ORCL": {"avg_volume": 29873907, "market_cap": 405109439681}, "CNX": {"avg_volume": 1892578, "market_cap": 4525868199}, "EAT": {"avg_volume": 1141406, "market_cap": 7945391739}, "RH": {"avg_volume": 953078, "market_cap": 3129450757}, "WSM": {"avg_volume": 1186401, "market_cap": 26110310989}, "LIF": {"avg_volume": 801517, "market_cap": 4421899353}, "GDXJ": {"avg_volume": 5557228}, "MTDR": {"avg_volume": 1734287, "market_cap": 6375310193}, "SBAC": {"avg_volume": 1005788, "market_cap": 20155154991}, "HMY": {"avg_volume": 4637765, "market_cap": 9540229248}, "CORT": {"avg_volume": 1089003, "market_cap": 9863464161}, "SILJ": {"avg_volume": 4557676}, "GNRC": {"avg_volume": 890492, "market_cap": 13771739376}, "ZETA": {"avg_volume": 9188333, "market_cap": 5356546218}, "HDB": {"avg_volume": 8523568, "market_cap": 136095335085}, "MGM": {"avg_volume": 4727111, "market_cap": 11994306170}, "CELH": {"avg_volume": 9204013, "market_cap": 7822595113}, "PI": {"avg_volume": 469784, "market_cap": 4387036378}, "IRTC": {"avg_volume": 555616, "market_cap": 3816311350}, "AVAV": {"avg_volume": 1582944, "market_cap": 7316909070}, "PAAS": {"avg_volume": 4912015, "market_cap": 18400353728}, "APTV": {"avg_volume": 3470921, "market_cap": 12817855255}, "SNX": {"avg_volume": 855997, "market_cap": 20111225644}, "PM": {"avg_volume": 4958157, "market_cap": 283065450000}, "FOXA": {"avg_volume": 5463919, "market_cap": 22725022837}, "SMTC": {"avg_volume": 3651819, "market_cap": 12680668954}, "BROS": {"avg_volume": 4031631, "market_cap": 9268733207}, "EME": {"avg_volume": 396327, "market_cap": 34814671533}, "GM": {"avg_volume": 7615629, "market_cap": 70194634054}, "CART": {"avg_volume": 4204994, "market_cap": 11373092556}, "AGCO": {"avg_volume": 728035, "market_cap": 8277742784}, "AEM": {"avg_volume": 2539538, "market_cap": 73440319686}, "MRNA": {"avg_volume": 7857533, "market_cap": 27088596569}, "HSBC": {"avg_volume": 1594425, "market_cap": 339843203410}, "SCCO": {"avg_volume": 1370873, "market_cap": 146699982737}, "CBRL": {"avg_volume": 1266282, "market_cap": 1126960572}, "PBF": {"avg_volume": 2892384, "market_cap": 6291643885}, "BFAM": {"avg_volume": 1222826, "market_cap": 3856595215}, "WLK": {"avg_volume": 1130417, "market_cap": 9672000768}, "EMBJ": {"avg_volume": 1490313, "market_cap": 11747023472}, "MSTR": {"avg_volume": 21283576, "market_cap": 33859213082}, "AG": {"avg_volume": 12602928, "market_cap": 8369394554}, "HPE": {"avg_volume": 25466670, "market_cap": 64276840121}, "MELI": {"avg_volume": 535025, "market_cap": 93902332958}, "RBRK": {"avg_volume": 3780247, "market_cap": 17367813833}, "INSM": {"avg_volume": 3742177, "market_cap": 25058750992}, "SIVR": {"avg_volume": 1552028}, "OC": {"avg_volume": 1255348, "market_cap": 11543735020}, "ALK": {"avg_volume": 3635077, "market_cap": 5506819888}, "ALNY": {"avg_volume": 1223403, "market_cap": 39888217613}, "FCX": {"avg_volume": 14860404, "market_cap": 88438683552}, "MU": {"avg_volume": 50971877, "market_cap": 1106014698987}, "CHRD": {"avg_volume": 797924, "market_cap": 6608961058}, "KGC": {"avg_volume": 8354387, "market_cap": 28825801707}, "W": {"avg_volume": 3930929, "market_cap": 11778048048}, "MBLY": {"avg_volume": 6609217, "market_cap": 8042877807}, "UNG": {"avg_volume": 7929502}, "BOOT": {"avg_volume": 705526, "market_cap": 4892922942}, "HAE": {"avg_volume": 884122, "market_cap": 3462529555}, "ATRO": {"avg_volume": 746932, "market_cap": 3577759580}, "INSP": {"avg_volume": 1162058, "market_cap": 1491368750}, "NYT": {"avg_volume": 1918271, "market_cap": 12133227768}, "WELL": {"avg_volume": 3425467, "market_cap": 163482724890}, "BE": {"avg_volume": 12175782, "market_cap": 69577814725}, "MCHI": {"avg_volume": 3036338}, "CRK": {"avg_volume": 2643512, "market_cap": 3794550171}, "DJT": {"avg_volume": 4423079, "market_cap": 2365185680}, "WHR": {"avg_volume": 2906957, "market_cap": 2639597566}, "HOOD": {"avg_volume": 31245878, "market_cap": 100829552331}, "SLVP": {"avg_volume": 363954}, "SLV": {"avg_volume": 22159642}, "COKE": {"avg_volume": 581770, "market_cap": 11934978117}, "WIX": {"avg_volume": 1981690, "market_cap": 2098334455}, "JLL": {"avg_volume": 399652, "market_cap": 15051931586}, "GME": {"avg_volume": 7315232, "market_cap": 9727626588}, "AR": {"avg_volume": 4822736, "market_cap": 10295850138}, "MIRM": {"avg_volume": 995393, "market_cap": 7447637086}}