{"GFS": {"price": 89.79, "prev_close": 85.83, "change_pct": 0.0461, "week_closes": [80.74, 81.38, 83.98, 79.92, 80.64, 85.83, 89.79]}, "CAVA": {"price": 83.33, "prev_close": 89.18, "change_pct": -0.0656, "week_closes": [88.25, 90.99, 89.52, 87.3, 88.05, 89.18, 83.33]}, "VIAV": {"price": 50.67, "prev_close": 47.17, "change_pct": 0.0742, "week_closes": [50.24, 53.46, 54.05, 50.1, 48.73, 47.17, 50.67]}, "FIVE": {"price": 193.7, "prev_close": 194.06, "change_pct": -0.0019, "week_closes": [201.97, 198.49, 193.92, 189.41, 191.26, 194.06, 193.7]}, "CZR": {"price": 29.33, "prev_close": 29.22, "change_pct": 0.0038, "week_closes": [29.51, 29.49, 29.5, 29.31, 29.21, 29.22, 29.33]}, "TIGO": {"price": 86.04, "prev_close": 84.41, "change_pct": 0.0193, "week_closes": [92.11, 93.77, 89.45, 87.31, 88.93, 84.41, 86.04]}, "RVMD": {"price": 165.9, "prev_close": 162.99, "change_pct": 0.0179, "week_closes": [149.23, 153.87, 160.06, 156.58, 157.77, 162.99, 165.9]}, "VSAT": {"price": 63.26, "prev_close": 64.13, "change_pct": -0.0136, "week_closes": [72.71, 70.17, 65.87, 62.45, 64.55, 64.13, 63.26]}, "EAT": {"price": 165.94, "prev_close": 164.89, "change_pct": 0.0064, "week_closes": [158.73, 159.32, 156.24, 153.55, 158.8, 164.89, 165.94]}, "CENX": {"price": 49.13, "prev_close": 51.71, "change_pct": -0.0499, "week_closes": [60.94, 61.19, 54.55, 53.55, 54.31, 51.71, 49.13]}, "LBRDK": {"price": 29.58, "prev_close": 29.62, "change_pct": -0.0014, "week_closes": [32.62, 34.19, 33.64, 33.21, 30.87, 29.62, 29.58]}, "RRX": {"price": 229.88, "prev_close": 226.78, "change_pct": 0.0137, "week_closes": [211.24, 212.31, 218.85, 222.53, 221.52, 226.78, 229.88]}, "MU": {"price": 1200.05, "prev_close": 1133.99, "change_pct": 0.0583, "week_closes": [995.87, 981.61, 1087.99, 1020.76, 1043.19, 1133.99, 1200.05]}, "NYT": {"price": 72.62, "prev_close": 73.06, "change_pct": -0.006, "week_closes": [74.2, 73.38, 73.8, 73.83, 74.46, 73.06, 72.62]}, "SKYT": {"price": 36.85, "prev_close": 36.57, "change_pct": 0.0077, "week_closes": [35.8, 36.61, 37.9, 36.13, 35.97, 36.57, 36.85]}, "ROKU": {"price": 135.88, "prev_close": 138.07, "change_pct": -0.0159, "week_closes": [119.64, 143.66, 140.9, 137.95, 137.29, 138.07, 135.88]}, "VSCO": {"price": 81.98, "prev_close": 78.52, "change_pct": 0.0441, "week_closes": [74.24, 78.78, 78.88, 79.42, 78.71, 78.52, 81.98]}, "SIL": {"price": 82.69, "prev_close": 83.73, "change_pct": -0.0124, "week_closes": [79.09, 81.68, 86.95, 89.23, 85.95, 83.73, 82.69]}, "MT": {"price": 63.54, "prev_close": 63.41, "change_pct": 0.0021, "week_closes": [69.09, 70.81, 69.21, 68.38, 65.03, 63.41, 63.54]}, "KEYS": {"price": 370.67, "prev_close": 363.67, "change_pct": 0.0192, "week_closes": [340.03, 350.67, 356.94, 350.29, 350.7, 363.67, 370.67]}, "WRBY": {"price": 26.46, "prev_close": 25.96, "change_pct": 0.0193, "week_closes": [25.86, 26.46, 26.38, 25.13, 24.22, 25.96, 26.46]}, "WPM": {"price": 120.6, "prev_close": 122.57, "change_pct": -0.0161, "week_closes": [112.66, 116.1, 123.94, 128.24, 125.85, 122.57, 120.6]}, "ALGM": {"price": 59.74, "prev_close": 59.0, "change_pct": 0.0125, "week_closes": [47.96, 50.4, 55.0, 53.29, 53.98, 59.0, 59.74]}, "PTEN": {"price": 9.98, "prev_close": 10.04, "change_pct": -0.006, "week_closes": [11.49, 11.49, 10.66, 10.35, 10.3, 10.04, 9.98]}, "EXPE": {"price": 237.59, "prev_close": 240.9, "change_pct": -0.0137, "week_closes": [224.66, 224.89, 236.98, 243.56, 239.47, 240.9, 237.59]}, "SNX": {"price": 284.55, "prev_close": 284.56, "change_pct": -0.0, "week_closes": [277.09, 280.65, 284.65, 282.11, 283.81, 284.56, 284.55]}, "AG": {"price": 17.78, "prev_close": 18.0, "change_pct": -0.0122, "week_closes": [16.92, 17.65, 18.9, 19.42, 18.55, 18.0, 17.78]}, "UPST": {"price": 31.08, "prev_close": 32.43, "change_pct": -0.0416, "week_closes": [31.79, 30.5, 32.36, 32.24, 30.46, 32.43, 31.08]}, "AU": {"price": 85.04, "prev_close": 90.87, "change_pct": -0.0642, "week_closes": [83.18, 86.3, 92.29, 93.93, 90.92, 90.87, 85.04]}, "INDV": {"price": 38.77, "prev_close": 38.3, "change_pct": 0.0123, "week_closes": [38.13, 38.48, 38.4, 38.01, 37.93, 38.3, 38.77]}, "MCHP": {"price": 101.97, "prev_close": 99.77, "change_pct": 0.0221, "week_closes": [92.94, 95.24, 100.32, 95.63, 94.11, 99.77, 101.97]}, "PM": {"price": 175.74, "prev_close": 178.4, "change_pct": -0.0149, "week_closes": [180.77, 184.3, 181.81, 184.06, 179.44, 178.4, 175.74]}, "AXSM": {"price": 249.05, "prev_close": 250.5, "change_pct": -0.0058, "week_closes": [253.77, 255.17, 253.4, 251.91, 252.16, 250.5, 249.05]}, "LULU": {"price": 105.2, "prev_close": 111.77, "change_pct": -0.0588, "week_closes": [121.84, 118.77, 116.21, 115.5, 111.76, 111.77, 105.2]}, "LNTH": {"price": 106.2, "prev_close": 103.86, "change_pct": 0.0225, "week_closes": [104.32, 104.52, 104.67, 105.03, 103.19, 103.86, 106.2]}, "PR": {"price": 18.91, "prev_close": 18.43, "change_pct": 0.026, "week_closes": [19.1, 19.34, 18.74, 18.67, 18.56, 18.43, 18.91]}, "ADM": {"price": 75.49, "prev_close": 75.1, "change_pct": 0.0052, "week_closes": [78.9, 80.24, 79.27, 78.02, 76.5, 75.1, 75.49]}, "G": {"price": 27.88, "prev_close": 28.25, "change_pct": -0.0131, "week_closes": [31.89, 32.06, 31.0, 31.32, 30.31, 28.25, 27.88]}, "APA": {"price": 34.06, "prev_close": 33.03, "change_pct": 0.0312, "week_closes": [36.78, 37.02, 34.77, 34.26, 33.93, 33.03, 34.06]}, "SATS": {"price": 105.66, "prev_close": 109.17, "change_pct": -0.0322, "week_closes": [128.13, 114.08, 117.87, 120.97, 111.7, 109.17, 105.66]}, "JBS": {"price": 11.93, "prev_close": 11.93, "change_pct": 0.0, "week_closes": [12.2, 12.54, 12.19, 12.3, 12.22, 11.93, 11.93]}, "SOC": {"price": 9.13, "prev_close": 10.12, "change_pct": -0.0978, "week_closes": [11.72, 10.88, 10.6, 9.99, 10.25, 10.12, 9.13]}, "OPCH": {"price": 21.45, "prev_close": 21.99, "change_pct": -0.0246, "week_closes": [20.78, 20.76, 21.23, 21.62, 21.71, 21.99, 21.45]}, "JBL": {"price": 369.99, "prev_close": 371.88, "change_pct": -0.0051, "week_closes": [376.89, 384.82, 385.63, 375.51, 374.98, 371.88, 369.99]}, "BEN": {"price": 34.26, "prev_close": 33.05, "change_pct": 0.0366, "week_closes": [31.81, 32.13, 32.51, 33.18, 33.29, 33.05, 34.26]}, "CPAY": {"price": 347.61, "prev_close": 345.28, "change_pct": 0.0067, "week_closes": [350.85, 356.11, 353.47, 360.37, 353.33, 345.28, 347.61]}, "TGTX": {"price": 54.36, "prev_close": 53.22, "change_pct": 0.0214, "week_closes": [48.05, 49.52, 50.3, 50.54, 51.5, 53.22, 54.36]}, "NSA": {"price": 45.03, "prev_close": 44.45, "change_pct": 0.013, "week_closes": [44.94, 45.15, 44.91, 44.69, 43.63, 44.45, 45.03]}, "CHYM": {"price": 16.95, "prev_close": 17.6, "change_pct": -0.0369, "week_closes": [17.25, 16.7, 17.64, 17.05, 16.6, 17.6, 16.95]}, "AAP": {"price": 56.76, "prev_close": 60.1, "change_pct": -0.0556, "week_closes": [60.62, 60.8, 61.04, 60.37, 58.1, 60.1, 56.76]}, "LQDA": {"price": 74.04, "prev_close": 71.07, "change_pct": 0.0418, "week_closes": [71.63, 71.23, 71.8, 68.01, 68.65, 71.07, 74.04]}, "HAL": {"price": 34.78, "prev_close": 34.93, "change_pct": -0.0043, "week_closes": [39.76, 39.6, 38.18, 37.2, 36.23, 34.93, 34.78]}, "STRL": {"price": 917.78, "prev_close": 861.88, "change_pct": 0.0649, "week_closes": [838.55, 858.99, 866.67, 857.76, 838.21, 861.88, 917.78]}, "TD": {"price": 120.06, "prev_close": 119.29, "change_pct": 0.0065, "week_closes": [116.25, 117.33, 117.34, 118.21, 118.5, 119.29, 120.06]}, "LRCX": {"price": 397.91, "prev_close": 389.04, "change_pct": 0.0228, "week_closes": [362.26, 366.55, 388.65, 369.08, 374.18, 389.04, 397.91]}, "PAYC": {"price": 122.57, "prev_close": 124.85, "change_pct": -0.0183, "week_closes": [132.24, 134.52, 134.69, 129.13, 123.72, 124.85, 122.57]}, "HE": {"price": 12.85, "prev_close": 13.02, "change_pct": -0.0131, "week_closes": [13.17, 13.38, 13.38, 13.47, 13.11, 13.02, 12.85]}, "SITM": {"price": 737.98, "prev_close": 729.04, "change_pct": 0.0123, "week_closes": [721.24, 729.89, 742.46, 684.86, 677.21, 729.04, 737.98]}, "EWY": {"price": 218.62, "prev_close": 219.2, "change_pct": -0.0026, "week_closes": [198.94, 197.45, 211.45, 205.91, 205.08, 219.2, 218.62]}, "ABNB": {"price": 138.79, "prev_close": 142.41, "change_pct": -0.0254, "week_closes": [130.87, 132.28, 138.96, 141.2, 140.54, 142.41, 138.79]}, "ON": {"price": 130.99, "prev_close": 121.62, "change_pct": 0.077, "week_closes": [115.96, 116.79, 125.9, 118.25, 112.92, 121.62, 130.99]}, "MTDR": {"price": 50.53, "prev_close": 49.56, "change_pct": 0.0196, "week_closes": [53.62, 54.05, 51.38, 51.21, 50.4, 49.56, 50.53]}, "SAIA": {"price": 440.5, "prev_close": 435.12, "change_pct": 0.0124, "week_closes": [487.14, 482.87, 474.19, 457.02, 425.86, 435.12, 440.5]}, "LSTR": {"price": 211.7, "prev_close": 207.4, "change_pct": 0.0207, "week_closes": [225.2, 224.27, 219.27, 216.15, 208.13, 207.4, 211.7]}, "LITE": {"price": 842.05, "prev_close": 850.0, "change_pct": -0.0094, "week_closes": [889.59, 921.56, 957.24, 875.36, 869.98, 850.0, 842.05]}, "AKAM": {"price": 119.41, "prev_close": 124.91, "change_pct": -0.044, "week_closes": [132.46, 133.5, 134.2, 132.31, 127.86, 124.91, 119.41]}, "KMX": {"price": 52.9, "prev_close": 53.66, "change_pct": -0.0142, "week_closes": [51.57, 51.26, 52.21, 52.11, 47.43, 53.66, 52.9]}, "AA": {"price": 57.8, "prev_close": 59.37, "change_pct": -0.0264, "week_closes": [68.98, 68.77, 64.16, 62.87, 61.73, 59.37, 57.8]}, "TAN": {"price": 61.47, "prev_close": 60.58, "change_pct": 0.0147, "week_closes": [62.3, 63.03, 62.7, 60.58, 58.45, 60.58, 61.47]}, "REMX": {"price": 97.18, "prev_close": 95.55, "change_pct": 0.0171, "week_closes": [92.96, 95.5, 96.89, 96.78, 96.04, 95.55, 97.18]}, "ATRO": {"price": 80.84, "prev_close": 80.56, "change_pct": 0.0035, "week_closes": [75.66, 76.62, 75.69, 75.5, 80.06, 80.56, 80.84]}, "KLAR": {"price": 18.0, "prev_close": 18.84, "change_pct": -0.0446, "week_closes": [16.4, 16.23, 17.6, 17.78, 17.86, 18.84, 18.0]}, "GNRC": {"price": 292.61, "prev_close": 279.15, "change_pct": 0.0482, "week_closes": [257.33, 262.36, 270.1, 265.66, 268.2, 279.15, 292.61]}, "WT": {"price": 18.65, "prev_close": 18.31, "change_pct": 0.0186, "week_closes": [17.28, 17.97, 18.32, 18.47, 18.15, 18.31, 18.65]}, "ALGN": {"price": 176.88, "prev_close": 182.08, "change_pct": -0.0286, "week_closes": [176.51, 174.84, 178.26, 179.52, 173.53, 182.08, 176.88]}, "RS": {"price": 404.46, "prev_close": 396.34, "change_pct": 0.0205, "week_closes": [410.43, 413.43, 405.92, 413.34, 404.11, 396.34, 404.46]}, "GDXJ": {"price": 105.68, "prev_close": 107.22, "change_pct": -0.0144, "week_closes": [101.08, 104.26, 111.88, 114.44, 109.79, 107.22, 105.68]}, "FCX": {"price": 69.29, "prev_close": 68.68, "change_pct": 0.0089, "week_closes": [66.34, 68.41, 70.13, 70.15, 69.06, 68.68, 69.29]}, "ONTO": {"price": 340.34, "prev_close": 333.76, "change_pct": 0.0197, "week_closes": [303.53, 323.88, 335.96, 316.15, 318.92, 333.76, 340.34]}, "ATI": {"price": 204.31, "prev_close": 201.34, "change_pct": 0.0148, "week_closes": [199.5, 198.48, 195.81, 196.31, 196.86, 201.34, 204.31]}, "SBAC": {"price": 187.87, "prev_close": 186.87, "change_pct": 0.0054, "week_closes": [203.65, 204.79, 195.82, 195.73, 191.57, 186.87, 187.87]}, "OLN": {"price": 21.54, "prev_close": 22.01, "change_pct": -0.0214, "week_closes": [24.2, 25.13, 25.3, 23.81, 23.0, 22.01, 21.54]}, "COLD": {"price": 14.12, "prev_close": 14.07, "change_pct": 0.0036, "week_closes": [14.67, 14.46, 14.55, 14.62, 14.15, 14.07, 14.12]}, "PTGX": {"price": 115.38, "prev_close": 112.86, "change_pct": 0.0223, "week_closes": [109.79, 109.78, 112.46, 110.64, 111.44, 112.86, 115.38]}, "SAIC": {"price": 99.08, "prev_close": 102.39, "change_pct": -0.0323, "week_closes": [114.93, 113.81, 109.39, 108.87, 106.73, 102.39, 99.08]}, "APG": {"price": 42.81, "prev_close": 42.54, "change_pct": 0.0063, "week_closes": [42.66, 42.34, 41.66, 42.5, 41.81, 42.54, 42.81]}, "SQM": {"price": 78.32, "prev_close": 79.69, "change_pct": -0.0172, "week_closes": [80.44, 84.12, 83.27, 83.11, 82.99, 79.69, 78.32]}, "POWL": {"price": 302.43, "prev_close": 297.2, "change_pct": 0.0176, "week_closes": [290.5, 294.75, 303.53, 292.7, 294.03, 297.2, 302.43]}, "MKSI": {"price": 417.14, "prev_close": 406.37, "change_pct": 0.0265, "week_closes": [345.32, 355.69, 375.32, 366.31, 371.26, 406.37, 417.14]}, "LSCC": {"price": 154.61, "prev_close": 153.72, "change_pct": 0.0058, "week_closes": [142.86, 144.53, 148.97, 143.48, 139.86, 153.72, 154.61]}, "ARRY": {"price": 8.48, "prev_close": 8.0, "change_pct": 0.06, "week_closes": [7.45, 7.77, 8.08, 7.86, 7.66, 8.0, 8.48]}, "DVA": {"price": 214.93, "prev_close": 207.91, "change_pct": 0.0338, "week_closes": [203.83, 208.66, 209.75, 208.98, 210.58, 207.91, 214.93]}, "PAAS": {"price": 48.72, "prev_close": 49.0, "change_pct": -0.0057, "week_closes": [46.53, 48.14, 50.97, 51.92, 50.46, 49.0, 48.72]}, "NTLA": {"price": 15.78, "prev_close": 15.67, "change_pct": 0.007, "week_closes": [12.35, 12.11, 14.92, 14.55, 15.2, 15.67, 15.78]}, "BLSH": {"price": 24.47, "prev_close": 24.1, "change_pct": 0.0154, "week_closes": [27.5, 27.21, 28.6, 25.96, 23.86, 24.1, 24.47]}, "LKQ": {"price": 25.45, "prev_close": 25.8, "change_pct": -0.0136, "week_closes": [25.98, 26.2, 26.14, 26.24, 25.02, 25.8, 25.45]}, "SLVP": {"price": 32.62, "prev_close": 33.05, "change_pct": -0.013, "week_closes": [31.24, 32.29, 34.45, 35.26, 33.87, 33.05, 32.62]}, "DOCN": {"price": 156.75, "prev_close": 173.27, "change_pct": -0.0953, "week_closes": [174.75, 170.44, 181.29, 174.18, 177.81, 173.27, 156.75]}, "SM": {"price": 27.38, "prev_close": 27.14, "change_pct": 0.0088, "week_closes": [31.28, 31.15, 28.47, 28.06, 28.09, 27.14, 27.38]}, "MTZ": {"price": 396.77, "prev_close": 379.66, "change_pct": 0.0451, "week_closes": [358.5, 362.97, 371.85, 369.35, 374.91, 379.66, 396.77]}, "CBRL": {"price": 47.3, "prev_close": 47.34, "change_pct": -0.0008, "week_closes": [45.5, 46.69, 43.49, 43.75, 43.88, 47.34, 47.3]}, "CE": {"price": 50.3, "prev_close": 51.16, "change_pct": -0.0168, "week_closes": [51.67, 53.48, 53.77, 51.93, 51.23, 51.16, 50.3]}, "SLNO": {"price": 53.01, "prev_close": 53.01, "change_pct": 0.0, "week_closes": [52.95, 52.94, 52.93, 52.95, 52.99, 53.01, 53.01]}, "STM": {"price": 79.93, "prev_close": 78.39, "change_pct": 0.0196, "week_closes": [78.12, 77.3, 78.95, 74.55, 73.36, 78.39, 79.93]}, "CIEN": {"price": 438.01, "prev_close": 428.22, "change_pct": 0.0229, "week_closes": [445.22, 445.98, 463.41, 430.3, 436.72, 428.22, 438.01]}, "BUD": {"price": 80.75, "prev_close": 80.74, "change_pct": 0.0001, "week_closes": [82.27, 82.91, 81.48, 82.35, 80.68, 80.74, 80.75]}, "WLK": {"price": 78.17, "prev_close": 80.28, "change_pct": -0.0263, "week_closes": [87.27, 88.5, 87.45, 84.33, 83.48, 80.28, 78.17]}, "PBR": {"price": 16.92, "prev_close": 16.75, "change_pct": 0.0101, "week_closes": [18.24, 18.38, 17.34, 17.05, 16.79, 16.75, 16.92]}, "AGI": {"price": 31.41, "prev_close": 36.34, "change_pct": -0.1357, "week_closes": [34.49, 35.2, 37.64, 38.42, 37.31, 36.34, 31.41]}, "STX": {"price": 1077.3, "prev_close": 1070.23, "change_pct": 0.0066, "week_closes": [868.09, 931.04, 1018.8, 1031.34, 1066.07, 1070.23, 1077.3]}, "VICR": {"price": 359.17, "prev_close": 331.37, "change_pct": 0.0839, "week_closes": [298.06, 303.77, 322.41, 320.46, 325.17, 331.37, 359.17]}, "VRSN": {"price": 247.8, "prev_close": 264.64, "change_pct": -0.0636, "week_closes": [279.57, 279.89, 272.96, 273.87, 264.92, 264.64, 247.8]}, "MLTX": {"price": 21.72, "prev_close": 19.21, "change_pct": 0.1307, "week_closes": [17.75, 18.69, 19.19, 18.98, 19.19, 19.21, 21.72]}, "B": {"price": 39.83, "prev_close": 40.34, "change_pct": -0.0126, "week_closes": [39.1, 40.2, 41.83, 42.77, 41.29, 40.34, 39.83]}, "ZIM": {"price": 25.21, "prev_close": 24.34, "change_pct": 0.0357, "week_closes": [25.91, 26.23, 24.92, 24.46, 23.98, 24.34, 25.21]}, "KRMN": {"price": 47.83, "prev_close": 50.37, "change_pct": -0.0504, "week_closes": [49.58, 47.83, 48.27, 51.7, 52.03, 50.37, 47.83]}, "ALSN": {"price": 121.1, "prev_close": 119.1, "change_pct": 0.0168, "week_closes": [115.52, 117.35, 119.47, 121.03, 118.86, 119.1, 121.1]}, "MASI": {"price": 179.95, "prev_close": 179.95, "change_pct": 0.0, "week_closes": [178.9, 178.82, 179.94, 179.95, 179.95, 179.95, 179.95]}, "WDC": {"price": 741.29, "prev_close": 746.23, "change_pct": -0.0066, "week_closes": [529.29, 562.93, 653.53, 681.08, 712.13, 746.23, 741.29]}, "CAR": {"price": 185.43, "prev_close": 188.43, "change_pct": -0.0159, "week_closes": [189.61, 187.12, 190.07, 185.49, 180.88, 188.43, 185.43]}, "OGN": {"price": 13.4, "prev_close": 13.43, "change_pct": -0.0022, "week_closes": [13.45, 13.44, 13.44, 13.42, 13.42, 13.43, 13.4]}, "DOW": {"price": 30.95, "prev_close": 31.73, "change_pct": -0.0246, "week_closes": [33.63, 33.85, 33.23, 32.96, 32.5, 31.73, 30.95]}, "HCC": {"price": 88.76, "prev_close": 90.58, "change_pct": -0.0201, "week_closes": [94.02, 98.11, 95.89, 93.47, 95.07, 90.58, 88.76]}, "SEB": {"price": 4815.02, "prev_close": 4795.0, "change_pct": 0.0042, "week_closes": [5223.98, 5317.39, 5198.05, 5067.01, 4867.39, 4795.0, 4815.02]}, "RIVN": {"price": 15.38, "prev_close": 16.52, "change_pct": -0.069, "week_closes": [15.54, 16.76, 16.68, 15.93, 16.26, 16.52, 15.38]}, "SGML": {"price": 13.02, "prev_close": 13.65, "change_pct": -0.0462, "week_closes": [14.73, 15.98, 15.4, 14.8, 14.8, 13.65, 13.02]}, "LINE": {"price": 40.98, "prev_close": 41.38, "change_pct": -0.0097, "week_closes": [44.57, 44.42, 43.37, 42.83, 41.53, 41.38, 40.98]}, "LNC": {"price": 37.96, "prev_close": 37.17, "change_pct": 0.0213, "week_closes": [36.6, 37.3, 37.57, 37.97, 37.39, 37.17, 37.96]}, "TXN": {"price": 328.73, "prev_close": 322.86, "change_pct": 0.0182, "week_closes": [297.1, 301.12, 313.34, 305.71, 301.88, 322.86, 328.73]}, "PEN": {"price": 316.67, "prev_close": 317.2, "change_pct": -0.0017, "week_closes": [318.32, 318.71, 318.21, 318.46, 316.16, 317.2, 316.67]}, "CROX": {"price": 126.5, "prev_close": 125.05, "change_pct": 0.0116, "week_closes": [125.87, 124.71, 126.27, 127.08, 124.53, 125.05, 126.5]}, "LYB": {"price": 58.31, "prev_close": 60.07, "change_pct": -0.0293, "week_closes": [63.47, 64.58, 63.3, 62.59, 61.81, 60.07, 58.31]}, "HIMS": {"price": 33.84, "prev_close": 35.47, "change_pct": -0.046, "week_closes": [28.87, 26.82, 30.17, 31.47, 31.89, 35.47, 33.84]}, "CVS": {"price": 102.88, "prev_close": 98.32, "change_pct": 0.0464, "week_closes": [100.48, 101.96, 100.68, 100.72, 99.16, 98.32, 102.88]}, "OVV": {"price": 54.13, "prev_close": 52.41, "change_pct": 0.0328, "week_closes": [56.23, 57.15, 54.31, 53.5, 53.61, 52.41, 54.13]}, "COHR": {"price": 403.67, "prev_close": 389.57, "change_pct": 0.0362, "week_closes": [363.58, 385.03, 413.84, 382.81, 378.85, 389.57, 403.67]}, "GEV": {"price": 1131.24, "prev_close": 1109.73, "change_pct": 0.0194, "week_closes": [906.33, 940.18, 978.57, 982.35, 1048.86, 1109.73, 1131.24]}, "TGT": {"price": 130.6, "prev_close": 130.74, "change_pct": -0.0011, "week_closes": [132.64, 135.23, 133.17, 133.4, 127.81, 130.74, 130.6]}, "VRT": {"price": 349.58, "prev_close": 333.05, "change_pct": 0.0496, "week_closes": [297.82, 302.81, 311.93, 299.6, 317.58, 333.05, 349.58]}, "IFF": {"price": 76.67, "prev_close": 76.72, "change_pct": -0.0007, "week_closes": [77.1, 77.86, 77.95, 77.44, 75.65, 76.72, 76.67]}, "NOVT": {"price": 155.67, "prev_close": 155.3, "change_pct": 0.0024, "week_closes": [162.41, 160.53, 156.63, 155.13, 151.43, 155.3, 155.67]}, "MRNA": {"price": 59.76, "prev_close": 63.96, "change_pct": -0.0657, "week_closes": [49.64, 49.91, 52.13, 55.4, 61.8, 63.96, 59.76]}, "RGLD": {"price": 215.05, "prev_close": 214.82, "change_pct": 0.0011, "week_closes": [204.57, 207.57, 215.52, 221.53, 218.42, 214.82, 215.05]}, "FNV": {"price": 218.26, "prev_close": 219.26, "change_pct": -0.0046, "week_closes": [207.91, 209.46, 222.35, 230.17, 226.93, 219.26, 218.26]}, "FOLD": {"price": 14.49, "prev_close": 14.49, "change_pct": 0.0, "week_closes": [14.46, 14.46, 14.46, 14.46, 14.46, 14.49, 14.49]}, "ESLT": {"price": 779.25, "prev_close": 788.23, "change_pct": -0.0114, "week_closes": [913.2, 854.06, 814.65, 821.99, 821.82, 788.23, 779.25]}, "ACMR": {"price": 103.6, "prev_close": 109.87, "change_pct": -0.0571, "week_closes": [91.7, 93.95, 95.21, 91.18, 96.19, 109.87, 103.6]}, "HSIC": {"price": 79.54, "prev_close": 79.92, "change_pct": -0.0048, "week_closes": [80.22, 81.25, 81.09, 81.21, 79.97, 79.92, 79.54]}, "KVUE": {"price": 18.13, "prev_close": 18.12, "change_pct": 0.0006, "week_closes": [18.07, 18.14, 18.25, 18.43, 18.01, 18.12, 18.13]}, "ICLN": {"price": 21.61, "prev_close": 21.1, "change_pct": 0.0242, "week_closes": [20.68, 20.86, 21.03, 20.82, 20.48, 21.1, 21.61]}, "KNX": {"price": 76.42, "prev_close": 74.15, "change_pct": 0.0306, "week_closes": [82.45, 81.54, 79.25, 77.34, 73.01, 74.15, 76.42]}, "TTMI": {"price": 221.44, "prev_close": 216.44, "change_pct": 0.0231, "week_closes": [187.21, 194.05, 206.66, 199.58, 202.7, 216.44, 221.44]}, "DINO": {"price": 64.62, "prev_close": 64.5, "change_pct": 0.0019, "week_closes": [69.9, 71.26, 67.25, 66.58, 65.91, 64.5, 64.62]}, "DAR": {"price": 53.38, "prev_close": 53.68, "change_pct": -0.0056, "week_closes": [57.0, 56.99, 56.12, 55.18, 53.79, 53.68, 53.38]}, "DG": {"price": 115.06, "prev_close": 113.45, "change_pct": 0.0142, "week_closes": [114.34, 114.8, 116.39, 113.75, 108.69, 113.45, 115.06]}, "RKT": {"price": 13.44, "prev_close": 14.42, "change_pct": -0.068, "week_closes": [13.43, 13.07, 13.91, 13.92, 13.22, 14.42, 13.44]}}